{
    "update_time": "2026-06-24 18:00:50",
    "intersection": [
        {
            "股票代號": "2432",
            "股票名稱": "倚天酷碁-創",
            "產業面": "電腦及週邊",
            "熱門程度": "高",
            "現價": 31.95,
            "單日漲跌幅(%)": 9.98,
            "成交量(張)": 546,
            "資本額(億)": 6.19,
            "每股盈餘(EPS)": 1.86,
            "本益比": 17.18
        },
        {
            "股票代號": "8024",
            "股票名稱": "佑華",
            "產業面": "半導體",
            "熱門程度": "高",
            "現價": 15.1,
            "單日漲跌幅(%)": 9.82,
            "成交量(張)": 786,
            "資本額(億)": 4.52,
            "每股盈餘(EPS)": -2.55,
            "本益比": null
        }
    ],
    "original_strategy": [
        {
            "股票代號": "1730",
            "股票名稱": "花仙子",
            "產業面": "Household & Personal Products",
            "熱門程度": "一般",
            "現價": 53.6,
            "單日漲跌幅(%)": 0.19,
            "成交量(張)": 74,
            "資本額(億)": 6.32,
            "每股盈餘(EPS)": 4.5,
            "本益比": 11.91
        },
        {
            "股票代號": "2415",
            "股票名稱": "錩新",
            "產業面": "Metal Fabrication",
            "熱門程度": "一般",
            "現價": 31.1,
            "單日漲跌幅(%)": 2.98,
            "成交量(張)": 642,
            "資本額(億)": 9.0,
            "每股盈餘(EPS)": 1.81,
            "本益比": 17.18
        },
        {
            "股票代號": "2727",
            "股票名稱": "王品",
            "產業面": "Restaurants",
            "熱門程度": "一般",
            "現價": 246.5,
            "單日漲跌幅(%)": 0.0,
            "成交量(張)": 333,
            "資本額(億)": 8.29,
            "每股盈餘(EPS)": 15.55,
            "本益比": 15.85
        },
        {
            "股票代號": "3588",
            "股票名稱": "通嘉",
            "產業面": "半導體",
            "熱門程度": "一般",
            "現價": 75.9,
            "單日漲跌幅(%)": 10.0,
            "成交量(張)": 3548,
            "資本額(億)": 6.2,
            "每股盈餘(EPS)": 0.5,
            "本益比": 151.8
        },
        {
            "股票代號": "6573",
            "股票名稱": "虹揚-KY",
            "產業面": "半導體",
            "熱門程度": "高",
            "現價": 21.5,
            "單日漲跌幅(%)": 9.97,
            "成交量(張)": 3344,
            "資本額(億)": 8.05,
            "每股盈餘(EPS)": 1.23,
            "本益比": 17.48
        },
        {
            "股票代號": "6698",
            "股票名稱": "旭暉應材",
            "產業面": "電子零組件",
            "熱門程度": "高",
            "現價": 47.75,
            "單日漲跌幅(%)": 8.28,
            "成交量(張)": 2924,
            "資本額(億)": 6.58,
            "每股盈餘(EPS)": -1.65,
            "本益比": null
        },
        {
            "股票代號": "6831",
            "股票名稱": "邁科",
            "產業面": "Specialty Industrial Machinery",
            "熱門程度": "一般",
            "現價": 852.0,
            "單日漲跌幅(%)": 2.65,
            "成交量(張)": 1820,
            "資本額(億)": 6.75,
            "每股盈餘(EPS)": 4.98,
            "本益比": 171.08
        },
        {
            "股票代號": "2432",
            "股票名稱": "倚天酷碁-創",
            "產業面": "電腦及週邊",
            "熱門程度": "高",
            "現價": 31.95,
            "單日漲跌幅(%)": 9.98,
            "成交量(張)": 546,
            "資本額(億)": 6.19,
            "每股盈餘(EPS)": 1.86,
            "本益比": 17.18
        },
        {
            "股票代號": "2061",
            "股票名稱": "風青",
            "產業面": "Electrical Equipment & Parts",
            "熱門程度": "一般",
            "現價": 63.8,
            "單日漲跌幅(%)": 10.0,
            "成交量(張)": 969,
            "資本額(億)": 5.74,
            "每股盈餘(EPS)": -0.97,
            "本益比": null
        },
        {
            "股票代號": "3114",
            "股票名稱": "好德",
            "產業面": "Industrial Distribution",
            "熱門程度": "高",
            "現價": 52.5,
            "單日漲跌幅(%)": 9.83,
            "成交量(張)": 3522,
            "資本額(億)": 6.44,
            "每股盈餘(EPS)": 2.21,
            "本益比": 23.76
        },
        {
            "股票代號": "5236",
            "股票名稱": "凌陽創新",
            "產業面": "半導體",
            "熱門程度": "一般",
            "現價": 179.5,
            "單日漲跌幅(%)": 1.7,
            "成交量(張)": 327,
            "資本額(億)": 6.0,
            "每股盈餘(EPS)": 8.58,
            "本益比": 20.92
        },
        {
            "股票代號": "5299",
            "股票名稱": "杰力",
            "產業面": "半導體",
            "熱門程度": "一般",
            "現價": 131.5,
            "單日漲跌幅(%)": 1.15,
            "成交量(張)": 1714,
            "資本額(億)": 5.09,
            "每股盈餘(EPS)": 4.81,
            "本益比": 27.34
        },
        {
            "股票代號": "5464",
            "股票名稱": "霖宏",
            "產業面": "電子零組件",
            "熱門程度": "一般",
            "現價": 98.0,
            "單日漲跌幅(%)": 9.99,
            "成交量(張)": 2781,
            "資本額(億)": 7.11,
            "每股盈餘(EPS)": -2.59,
            "本益比": null
        },
        {
            "股票代號": "5489",
            "股票名稱": "彩富",
            "產業面": "消費電子",
            "熱門程度": "高",
            "現價": 61.9,
            "單日漲跌幅(%)": 9.95,
            "成交量(張)": 1491,
            "資本額(億)": 9.85,
            "每股盈餘(EPS)": 1.99,
            "本益比": 31.11
        },
        {
            "股票代號": "6204",
            "股票名稱": "艾華",
            "產業面": "電子零組件",
            "熱門程度": "一般",
            "現價": 122.0,
            "單日漲跌幅(%)": 2.95,
            "成交量(張)": 1515,
            "資本額(億)": 2.31,
            "每股盈餘(EPS)": 1.19,
            "本益比": 102.52
        },
        {
            "股票代號": "6223",
            "股票名稱": "旺矽",
            "產業面": "Semiconductor Equipment & Materials",
            "熱門程度": "一般",
            "現價": 7175.0,
            "單日漲跌幅(%)": 7.41,
            "成交量(張)": 1216,
            "資本額(億)": 9.8,
            "每股盈餘(EPS)": 33.4,
            "本益比": 214.82
        },
        {
            "股票代號": "6241",
            "股票名稱": "鑫永洋",
            "產業面": "通信網路",
            "熱門程度": "一般",
            "現價": 15.1,
            "單日漲跌幅(%)": 4.5,
            "成交量(張)": 508,
            "資本額(億)": 4.87,
            "每股盈餘(EPS)": -0.16,
            "本益比": null
        },
        {
            "股票代號": "6693",
            "股票名稱": "廣閎科",
            "產業面": "半導體",
            "熱門程度": "一般",
            "現價": 251.0,
            "單日漲跌幅(%)": 6.13,
            "成交量(張)": 1028,
            "資本額(億)": 4.5,
            "每股盈餘(EPS)": -0.09,
            "本益比": null
        },
        {
            "股票代號": "7712",
            "股票名稱": "博盛半導體",
            "產業面": "半導體",
            "熱門程度": "一般",
            "現價": 204.0,
            "單日漲跌幅(%)": 2.0,
            "成交量(張)": 2766,
            "資本額(億)": 3.26,
            "每股盈餘(EPS)": 5.4,
            "本益比": 37.78
        },
        {
            "股票代號": "7828",
            "股票名稱": "創新服務",
            "產業面": "Specialty Industrial Machinery",
            "熱門程度": "一般",
            "現價": 2325.0,
            "單日漲跌幅(%)": 3.79,
            "成交量(張)": 190,
            "資本額(億)": 4.05,
            "每股盈餘(EPS)": 6.27,
            "本益比": 370.81
        },
        {
            "股票代號": "8024",
            "股票名稱": "佑華",
            "產業面": "半導體",
            "熱門程度": "高",
            "現價": 15.1,
            "單日漲跌幅(%)": 9.82,
            "成交量(張)": 786,
            "資本額(億)": 4.52,
            "每股盈餘(EPS)": -2.55,
            "本益比": null
        },
        {
            "股票代號": "8091",
            "股票名稱": "翔名",
            "產業面": "半導體",
            "熱門程度": "一般",
            "現價": 286.0,
            "單日漲跌幅(%)": 1.96,
            "成交量(張)": 1926,
            "資本額(億)": 5.34,
            "每股盈餘(EPS)": 5.55,
            "本益比": 51.53
        }
    ],
    "ai_strategy": [
        {
            "股票代號": "2460",
            "股票名稱": "建通",
            "產業面": "電子零組件",
            "熱門程度": "高",
            "現價": 40.45,
            "單日漲跌幅(%)": 9.92,
            "成交量(張)": 7740,
            "資本額(億)": 16.92,
            "每股盈餘(EPS)": -3.0,
            "本益比": null
        },
        {
            "股票代號": "6243",
            "股票名稱": "迅杰",
            "產業面": "半導體",
            "熱門程度": "高",
            "現價": 45.65,
            "單日漲跌幅(%)": 10.0,
            "成交量(張)": 8692,
            "資本額(億)": 4.53,
            "每股盈餘(EPS)": -0.52,
            "本益比": null
        },
        {
            "股票代號": "2432",
            "股票名稱": "倚天酷碁-創",
            "產業面": "電腦及週邊",
            "熱門程度": "高",
            "現價": 31.95,
            "單日漲跌幅(%)": 9.98,
            "成交量(張)": 546,
            "資本額(億)": 6.19,
            "每股盈餘(EPS)": 1.86,
            "本益比": 17.18
        },
        {
            "股票代號": "3122",
            "股票名稱": "笙泉",
            "產業面": "半導體",
            "熱門程度": "高",
            "現價": 34.9,
            "單日漲跌幅(%)": 9.92,
            "成交量(張)": 841,
            "資本額(億)": 4.08,
            "每股盈餘(EPS)": -1.75,
            "本益比": null
        },
        {
            "股票代號": "3128",
            "股票名稱": "昇銳",
            "產業面": "Security & Protection Services",
            "熱門程度": "極高",
            "現價": 25.8,
            "單日漲跌幅(%)": 6.17,
            "成交量(張)": 1751,
            "資本額(億)": 4.73,
            "每股盈餘(EPS)": 1.28,
            "本益比": 20.16
        },
        {
            "股票代號": "6129",
            "股票名稱": "普誠",
            "產業面": "半導體",
            "熱門程度": "高",
            "現價": 18.9,
            "單日漲跌幅(%)": 9.88,
            "成交量(張)": 3981,
            "資本額(億)": 18.09,
            "每股盈餘(EPS)": -1.09,
            "本益比": null
        },
        {
            "股票代號": "6788",
            "股票名稱": "華景電",
            "產業面": "Electrical Equipment & Parts",
            "熱門程度": "高",
            "現價": 456.0,
            "單日漲跌幅(%)": 6.29,
            "成交量(張)": 2779,
            "資本額(億)": 3.87,
            "每股盈餘(EPS)": 17.25,
            "本益比": 26.43
        },
        {
            "股票代號": "8024",
            "股票名稱": "佑華",
            "產業面": "半導體",
            "熱門程度": "高",
            "現價": 15.1,
            "單日漲跌幅(%)": 9.82,
            "成交量(張)": 786,
            "資本額(億)": 4.52,
            "每股盈餘(EPS)": -2.55,
            "本益比": null
        },
        {
            "股票代號": "8054",
            "股票名稱": "安國",
            "產業面": "電腦及週邊",
            "熱門程度": "高",
            "現價": 136.5,
            "單日漲跌幅(%)": 9.64,
            "成交量(張)": 19940,
            "資本額(億)": 10.58,
            "每股盈餘(EPS)": -3.19,
            "本益比": null
        },
        {
            "股票代號": "8234",
            "股票名稱": "新漢",
            "產業面": "電腦及週邊",
            "熱門程度": "極高",
            "現價": 70.7,
            "單日漲跌幅(%)": 9.95,
            "成交量(張)": 5636,
            "資本額(億)": 14.12,
            "每股盈餘(EPS)": 0.39,
            "本益比": 181.28
        }
    ]
}